oommftools/__init__.py
oommftools/__main__.py
oommftools/_about.py
oommftools/fnameutil.py
oommftools/odtchomp.py
oommftools/oommfconvert.py
oommftools/oommfdecode.py
oommftools/oommftools.py
oommftools-2.0.2.dist-info/DESCRIPTION.rst
oommftools-2.0.2.dist-info/METADATA
oommftools-2.0.2.dist-info/RECORD
oommftools-2.0.2.dist-info/WHEEL
oommftools-2.0.2.dist-info/metadata.json
oommftools-2.0.2.dist-info/top_level.txt
