Metadata-Version: 2.0
Name: oommftools
Version: 2.0.2
Summary: OOMMFTools is a set of drag-and-drop GUI utilities to assist in OOMMF postprocessing, including imageconversion and vector file manipulation.
Home-page: https://github.com/deparkes/OOMMFTools
Author: Duncan Parkes
Author-email: deparkes@gmail.com
License: GPLv2
Platform: UNKNOWN
Requires-Dist: numpy
Requires-Dist: scipy
Requires-Dist: wxpython
